Metadata-Version: 2.1
Name: thinks-dash-selectable-box
Version: 1.0.1
Summary: Dash Style change when selected Component
Author: thinkup-sol <s_matsumoto@thinkup-sol.co.jp>
License: MIT
Classifier: Framework :: Dash
License-File: LICENSE
